Claude2Api/__init__.py
Claude2Api/claude_2_api.py
gigathon-api/__init__.py
gigathon-api/gigathon_api_gigachat.py
gigathon-api/setup.py
kandinsky-api-gigachat/GigaChat.py
kandinsky-api-gigachat/Kandinsky.py
kandinsky-api-gigachat/__init__.py
claude_2_api-1.0.0.dist-info/METADATA
claude_2_api-1.0.0.dist-info/WHEEL
claude_2_api-1.0.0.dist-info/top_level.txt
claude_2_api-1.0.0.dist-info/RECORD
